luketils/__init__.py
luketils/colab/__init__.py
luketils/colab/get_strategy.py
luketils/colab/keras_cv_cuda.py
luketils/drawing/__init__.py
luketils/drawing/draw_bounding_boxes.py
luketils/utils/__init__.py
luketils/utils/ensure_exists.py
luketils/utils/experiment_name.py
luketils/utils/increase_resource_limit.py
luketils/utils/tf_cap_memory.py
luketils/utils/to_numpy.py
luketils/visualization/__init__.py
luketils/visualization/line_plot.py
luketils/visualization/plot_bounding_box_gallery.py
luketils/visualization/plot_gallery.py
luketils/visualization/plot_latents.py
luketils-0.1.9.dist-info/LICENSE
luketils-0.1.9.dist-info/METADATA
luketils-0.1.9.dist-info/WHEEL
luketils-0.1.9.dist-info/top_level.txt
luketils-0.1.9.dist-info/RECORD
